LICENSE
MANIFEST.in
README.md
requirements.txt
setup.py
django_auth_http_basic/__init__.py
django_auth_http_basic.egg-info/PKG-INFO
django_auth_http_basic.egg-info/SOURCES.txt
django_auth_http_basic.egg-info/dependency_links.txt
django_auth_http_basic.egg-info/requires.txt
django_auth_http_basic.egg-info/top_level.txt
tests/__init__.py
tests/manage.py
tests/test_http.py