Metadata-Version: 1.1
Name: django-auth-http-basic
Version: 20180405.0
Summary: Django authentication based based on HTTP basic authentication
Home-page: https://p.t73f.de/django-auth-http-basic
Author: Detlef Stern
Author-email: mail-python.org@yodod.de
License: APL2
Keywords: authentication django http basic auth
Platform: UNKNOWN
Classifier: Development Status :: 3 - Alpha
Classifier: Environment :: Web Environment
Classifier: Framework :: Django
Classifier: Intended Audience :: Developers
Classifier: License :: OSI Approved :: Apache Software License
Classifier: Programming Language :: Python :: 3.6
Classifier: Topic :: Internet :: WWW/HTTP
Classifier: Topic :: System :: Systems Administration :: Authentication/Directory
